rephrase/__init__.py
rephrase/main.py
rephrase/rephraser.py
rephrase-0.1.1.dist-info/METADATA
rephrase-0.1.1.dist-info/WHEEL
rephrase-0.1.1.dist-info/entry_points.txt
rephrase-0.1.1.dist-info/licenses/LICENSE
rephrase-0.1.1.dist-info/RECORD
