Metadata-Version: 2.4
Name: rephrase
Version: 0.1.1
Summary: A command-line tool to rephrase text in different styles using OpenAI's API.
Project-URL: Homepage, https://github.com/jayson-panganiban/rephrase
Project-URL: Source, https://github.com/jayson-panganiban/rephrase
Author-email: Jayson Panganiban <jsoncp@proton.me>
License: MIT License
License-File: LICENSE
Requires-Python: >=3.11
Requires-Dist: openai>=1.64.0
Requires-Dist: typer>=0.15.1
